{
  "font": {
    "body": {
      "family": {
        "value": "{font.palette.family.graphik}"
      },
      "family-fallback": {
        "1": {
          "value": "{font.palette.family.graphik-fallback.1}"
        },
        "2": {
          "value": "{font.palette.family.graphik-fallback.2}"
        }
      },
      "weight": {
        "value": "{font.palette.weight.400}"
      },
      "size": {
        "value": "{font.palette.size.200}"
      },
      "letter-spacing": {
        "value": "{font.palette.letter-spacing.000}"
      },
      "line-height": {
        "value": "{font.palette.line-height.350}"
      }
    }
  }
}
